{
  "name": "rutas_negro",
  "version": 32,
  "source-key": {
    "type": "figma",
    "file": "mWw7uoIKh232SbrwDLYSOe",
    "node": "258:776",
    "version": "5045563085",
    "component-id": "16e97fda55bef8d560e461d346c8059686c83d1f"
  },
  "default": "rutasNegro",
  "design": {
    "atoms": [
      {
        "type": "group",
        "id": "top_level",
        "root": "true"
      },
      {
        "type": "text",
        "id": "Rutas"
      },
      {
        "type": "group",
        "id": "circum:circle-chev-up"
      },
      {
        "type": "vector",
        "id": "icono"
      },
      {
        "type": "vector",
        "id": "Circulo"
      }
    ],
    "modes": {
      "rutasNegro": {
        "rules": [
          {
            "id": "top_level",
            "padding": {
              "left": "5.0",
              "top": "3.0",
              "right": "5.0",
              "bottom": "3.0"
            },
            "border-radius": "8.0",
            "tap-handler": "$on rutasNegro tapped",
            "size-constraints": {
              "width-constraints": {
                "sizing-mode": "shrink"
              },
              "height-constraints": {
                "sizing-mode": "shrink"
              }
            },
            "arrangement": "row",
            "children": [
              "Rutas",
              "circum:circle-chev-up"
            ],
            "item-spacing": "34.0",
            "background-color": {
              "alpha": "1.0",
              "hue": "0.0",
              "saturation": "0.0",
              "value": "0.0"
            },
            "clip-content": "false"
          },
          {
            "id": "Rutas",
            "size-constraints": {
              "width-constraints": {
                "sizing-mode": "fixed",
                "value": "29.0"
              },
              "height-constraints": {
                "sizing-mode": "fixed",
                "value": "16.0"
              }
            },
            "color": {
              "alpha": "1.0",
              "hue": "37.50000000000008",
              "saturation": "0.037914691943127965",
              "value": "0.8274509803921568"
            },
            "text-content": "Rutas",
            "overflow": "visible",
            "max-lines": "-1",
            "text-size": "13.0",
            "line-height": "1.2568359375",
            "typeface": "Fjalla One"
          },
          {
            "id": "circum:circle-chev-up",
            "relative-transform": [
              [
                "1.0",
                "0.0",
                "0.0"
              ],
              [
                "0.0",
                "-1.0",
                "0.0"
              ]
            ],
            "size-constraints": {
              "width-constraints": {
                "sizing-mode": "fixed",
                "value": "24.0"
              },
              "height-constraints": {
                "sizing-mode": "fixed",
                "value": "24.0"
              }
            },
            "is-structured": "false",
            "children": [
              "icono",
              "Circulo"
            ]
          },
          {
            "id": "icono",
            "margin": {
              "left": "8.508544921875",
              "top": "10.00853180885315",
              "right": "8.50852632522583",
              "bottom": "10.0037841796875"
            },
            "alignment": {
              "horizontal": {
                "attachment": "start",
                "offset": "0.0"
              },
              "vertical": {
                "attachment": "start",
                "offset": "0.000013113021850585938"
              }
            },
            "size-constraints": {
              "width-constraints": {
                "sizing-mode": "proportional",
                "value": "1.0"
              },
              "height-constraints": {
                "sizing-mode": "proportional",
                "value": "1.0"
              }
            },
            "vector-content": "icono.svg"
          },
          {
            "id": "Circulo",
            "margin": {
              "left": "2.0670166015625",
              "top": "2.0660018920898438",
              "right": "2.0669784545898438",
              "bottom": "2.0679931640625"
            },
            "alignment": {
              "horizontal": {
                "attachment": "start",
                "offset": "0.0"
              },
              "vertical": {
                "attachment": "start",
                "offset": "0.00000762939453125"
              }
            },
            "size-constraints": {
              "width-constraints": {
                "sizing-mode": "proportional",
                "value": "1.0"
              },
              "height-constraints": {
                "sizing-mode": "proportional",
                "value": "1.0"
              }
            },
            "vector-content": "circulo.svg"
          }
        ]
      }
    }
  },
  "parameters": {
    "on rutasNegro tapped": {
      "data-type": "void-callback",
      "required": false,
      "description": ""
    }
  },
  "previews": [
    {
      "design": "rutasNegro",
      "size": {
        "width": 97.0,
        "height": 30.0
      }
    }
  ],
  "adin-component-search-paths": [],
  "image-search-paths": [],
  "vector-search-paths": []
}